LICENSE
sudoku/__init__.py
sudoku/examples/__init__.py
sudoku/examples/boards.py
sudoku/examples/rate.py
sudoku/examples/shuffle.py
sudoku/examples/solve.py
sudoku/puzzle.py
sudoku/solvers/__init__.py
sudoku/solvers/solver.py
sudoku/solvers/strategy_solver.py
sudoku/strategies/__init__.py
sudoku/strategies/hidden_subset.py
sudoku/strategies/naked_subset.py
sudoku/strategies/refresh_candidates.py
sudoku/strategies/strategy.py
sudoku_tools-0.1.0.dist-info/entry_points.txt
sudoku_tools-0.1.0.dist-info/LICENSE
sudoku_tools-0.1.0.dist-info/WHEEL
sudoku_tools-0.1.0.dist-info/METADATA
sudoku_tools-0.1.0.dist-info/RECORD
