Metadata-Version: 2.1
Name: sudoku-tools
Version: 0.1.0
Summary: A collection of useful tools for generating, grading, solving, and transforming sudoku puzzles
Home-page: https://github.com/dawsonbooth/sudoku-tools
License: MIT
Author: Dawson Booth
Author-email: pypi@dawsonbooth.com
Requires-Python: >=3.7,<4.0
Classifier: Environment :: Console
Classifier: License :: OSI Approved :: MIT License
Classifier: Operating System :: OS Independent
Classifier: Programming Language :: Python :: 3
Classifier: Programming Language :: Python :: 3.7
Classifier: Programming Language :: Python :: 3.8
Classifier: Programming Language :: Python :: 3.9
Requires-Dist: numpy (>=1.20.2,<2.0.0)
Project-URL: Documentation, https://dawsonbooth.github.io/sudoku-tools
Project-URL: Repository, https://github.com/dawsonbooth/sudoku-tools
